Metadata-Version: 2.4
Name: solanab-jup-python-sdk
Version: 2.0.7
Summary: High-performance sync/async Python SDK for Jupiter Exchange APIs, powered by curl_cffi.
Project-URL: homepage, https://github.com/solanab/jup-python-sdk
Project-URL: repository, https://github.com/solanab/jup-python-sdk
Author-email: Fiji <charismoutafidis@gmail.com>, solanab <whiredj@gmail.com>
License: MIT
License-File: LICENSE
Keywords: jupiter,sdk,solana
Classifier: Development Status :: 5 - Production/Stable
Classifier: Intended Audience :: Developers
Classifier: License :: OSI Approved :: MIT License
Classifier: Operating System :: OS Independent
Classifier: Programming Language :: Python :: 3
Classifier: Programming Language :: Python :: 3.9
Classifier: Programming Language :: Python :: 3.10
Classifier: Programming Language :: Python :: 3.11
Classifier: Programming Language :: Python :: 3.12
Classifier: Programming Language :: Python :: 3.13
Classifier: Topic :: Software Development :: Libraries :: Python Modules
Requires-Python: >=3.9
Requires-Dist: base58>=2.1.1
Requires-Dist: curl-cffi>=0.12
Requires-Dist: pydantic>=2.11.3
Requires-Dist: python-dotenv>=1.1.1
Requires-Dist: solders>=0.26.0
Provides-Extra: dev
Requires-Dist: bandit>=1.7; extra == 'dev'
Requires-Dist: pip-audit>=2.8.0; extra == 'dev'
Requires-Dist: pre-commit>=4.1.0; extra == 'dev'
Requires-Dist: pyright>=1.1.0; extra == 'dev'
Requires-Dist: pytest-asyncio>=0.23.7; extra == 'dev'
Requires-Dist: pytest-cov>=6.1.1; extra == 'dev'
Requires-Dist: pytest>=8.3.4; extra == 'dev'
Requires-Dist: python-dotenv>=1.1.0; extra == 'dev'
Requires-Dist: ruff>=0.8.0; extra == 'dev'
